{
    "$schema": "https://json-schema.org/draft/2019-09/schema",
    "$id": "http://example.com/example.json",
    "type": "object",
    "default": {},
    "title": "Root Schema",
    "required": [
        "type",
        "name"
    ],
    "properties": {
        "type": {
            "type": "string",
            "default": "",
            "title": "The type Schema",
            "examples": [
                "show"
            ]
        },
        "name": {
            "type": "string",
            "default": "",
            "title": "The name Schema",
            "examples": [
                "Comedy Shows"
            ]
        }
    },
    "examples": [{
        "type": "show",
        "name": "Comedy Shows"
    }]
}